ftml_studio/__init__.py
ftml_studio/__main__.py
ftml_studio/cli/__init__.py
ftml_studio/components/__init__.py
ftml_studio/components/enhanced_text_edit.py
ftml_studio/converters/__init__.py
ftml_studio/converters/base.py
ftml_studio/converters/ftml_conversion_validator.py
ftml_studio/converters/json_converter.py
ftml_studio/converters/toml_converter.py
ftml_studio/converters/xml_converter.py
ftml_studio/converters/yaml_converter.py
ftml_studio/logger.py
ftml_studio/syntax/__init__.py
ftml_studio/syntax/ast_highlighter.py
ftml_studio/syntax/base_highlighter.py
ftml_studio/syntax/json_highlighter.py
ftml_studio/syntax/schema_highlighter.py
ftml_studio/syntax/toml_highlighter.py
ftml_studio/syntax/xml_highlighter.py
ftml_studio/syntax/yaml_highlighter.py
ftml_studio/ui/__init__.py
ftml_studio/ui/base_window.py
ftml_studio/ui/elements/__init__.py
ftml_studio/ui/elements/converter.py
ftml_studio/ui/elements/ftml_editor.py
ftml_studio/ui/elements/settings.py
ftml_studio/ui/elements/sidebar.py
ftml_studio/ui/icons/dark/converter.png
ftml_studio/ui/icons/dark/editor.png
ftml_studio/ui/icons/dark/menu.png
ftml_studio/ui/icons/dark/menu_close.png
ftml_studio/ui/icons/dark/menu_open.png
ftml_studio/ui/icons/dark/new.png
ftml_studio/ui/icons/dark/open.png
ftml_studio/ui/icons/dark/save.png
ftml_studio/ui/icons/dark/save_as.png
ftml_studio/ui/icons/dark/settings.png
ftml_studio/ui/icons/light/converter.png
ftml_studio/ui/icons/light/editor.png
ftml_studio/ui/icons/light/menu.png
ftml_studio/ui/icons/light/menu_close.png
ftml_studio/ui/icons/light/menu_open.png
ftml_studio/ui/icons/light/new.png
ftml_studio/ui/icons/light/open.png
ftml_studio/ui/icons/light/save.png
ftml_studio/ui/icons/light/save_as.png
ftml_studio/ui/icons/light/settings.png
ftml_studio/ui/main_window.py
ftml_studio/ui/themes/__init__.py
ftml_studio/ui/themes/theme_manager.py
ftml_studio-0.1.0a2.dist-info/entry_points.txt
ftml_studio-0.1.0a2.dist-info/LICENSE
ftml_studio-0.1.0a2.dist-info/METADATA
ftml_studio-0.1.0a2.dist-info/WHEEL
ftml_studio-0.1.0a2.dist-info/RECORD
