Metadata-Version: 2.1
Name: ftml-studio
Version: 0.1.0a2
Summary: A modern GUI editor and conversion tool for FTML markup language with syntax highlighting, error detection, and format conversion between FTML, JSON, YAML, TOML and XML.
License: LGPL-3.0
Author: DarrenHaba
Author-email: darrenhaba@live.com
Requires-Python: >=3.9,<3.14
Classifier: License :: OSI Approved :: GNU Lesser General Public License v3 (LGPLv3)
Classifier: Programming Language :: Python :: 3
Classifier: Programming Language :: Python :: 3.9
Classifier: Programming Language :: Python :: 3.10
Classifier: Programming Language :: Python :: 3.11
Classifier: Programming Language :: Python :: 3.12
Requires-Dist: flake8 (>=7.2.0,<8.0.0)
Requires-Dist: ftml (>=0.1.0a1,<0.2.0)
Requires-Dist: pyside6 (>=6.9.0,<7.0.0)
Requires-Dist: pyyaml (>=6.0.2,<7.0.0)
Requires-Dist: toml (>=0.10.2,<0.11.0)
Project-URL: Bug Tracker, https://github.com/DarrenHaba/ftml-studio/issues
Project-URL: Homepage, https://github.com/DarrenHaba/ftml-studio
Project-URL: Repository, https://github.com/DarrenHaba/ftml-studio
